{
  "overview": "Nordic Comfort 청키 니트 담요는 뛰어난 부드러움과 아름다운 스칸디나비아 스타일의 디자인으로 많은 사랑을 받고 있습니다. 고객들은 품질, 다양한 활용성, 훌륭한 가성비를 자주 칭찬하며, 개인 사용과 선물용 모두로 인기 있는 선택입니다.",
  "ratings": {
    "overall": 4.7,
    "totalReviews": 892
  },
  "satisfaction": [
    { "aspect": "부드러움", "score": 95, "summary": "예외적으로 부드러운 셔닐 소재가 보편적인 찬사를 받음." },
    { "aspect": "디자인", "score": 92, "summary": "청키 니트 패턴과 색상이 홈 데코에 높은 평가." },
    { "aspect": "내구성", "score": 85, "summary": "세탁 후에도 품질 유지, 보풀 최소화." },
    { "aspect": "보온성", "score": 78, "summary": "예상보다 가볍지만 사계절 사용에 적합." }
  ],
  "keywords": {
    "positive": ["정말 부드러운", "아름다운", "좋은 품질", "완벽한 선물", "멋진 질감"],
    "concerns": ["예상보다 가벼움", "초기 보풀"],
    "notable": ["세탁기 사용 가능", "청키 니트", "통기성"]
  },
  "strengths": [
    "손에 닿으면 럭셔리하게 느껴지는 프리미엄 셔닐 소재.",
    "우아한 질감을 더하는 아름다운 핸드니트 케이블 패턴.",
    "세탁기 사용 가능하며 여러 번 세탁 후에도 품질 유지.",
    "다양한 홈 데코 스타일에 어울리는 다양한 색상."
  ],
  "considerations": [
    "청키 니트 외관에 비해 무게가 예상보다 가벼울 수 있음.",
    "첫 세탁 시 약간의 보풀이 발생할 수 있음 (이후 멈춤).",
    "두꺼운 겨울용보다는 장식용 및 가벼운 보온용에 더 적합."
  ],
  "bestFor": "거실 공간에 아늑한 스칸디나비아 스타일을 더하고 싶은 홈 데코 애호가에게 완벽합니다. 선물, 영화 감상, 소파나 침대에 따뜻함을 더하는 데 훌륭한 선택.",
  "productInfo": {
    "material": "프리미엄 셔닐 원사",
    "dimensions": "50x60인치 (127x152 cm)",
    "features": "핸드니트 패턴, 세탁기 사용 가능, 가볍고 통기성 좋음"
  }
}

